{
  "system": "NoFails",
  "data": [
    {
      "id": "3node",
      "av": [
        "0node",
        "1node"
      ],
      "pv": [
        "2node",
        "4node"
      ],
      "gv": [
        "3node",
        "1node",
        "0node",
        "2node",
        "4node"
      ],
      "JoinsReceived": 0,
      "ForwardJoinsReceived": 1,
      "ForwardJoinsSent": 1,
      "NeighborRequestsReceived": 7403,
      "NeighborRequestsSent": 0,
      "DisconnectsReceived": 0,
      "DisconnectsSent": 0,
      "ShufflesReceived": 20,
      "ShufflesSent": 20,
      "BroadcastsSent": 6,
      "BroadcastsReceived": 10,
      "ResolveConflicts": 0,
      "ChecksIfAlive": 0
    },
    {
      "id": "4node",
      "av": [
        "0node",
        "2node"
      ],
      "pv": [
        "3node",
        "1node"
      ],
      "gv": [
        "3node",
        "4node",
        "1node",
        "0node",
        "2node"
      ],
      "JoinsReceived": 0,
      "ForwardJoinsReceived": 0,
      "ForwardJoinsSent": 0,
      "NeighborRequestsReceived": 0,
      "NeighborRequestsSent": 0,
      "DisconnectsReceived": 0,
      "DisconnectsSent": 0,
      "ShufflesReceived": 11,
      "ShufflesSent": 10,
      "BroadcastsSent": 6,
      "BroadcastsReceived": 6,
      "ResolveConflicts": 0,
      "ChecksIfAlive": 0
    },
    {
      "id": "1node",
      "av": [
        "2node",
        "3node"
      ],
      "pv": [
        "0node",
        "4node"
      ],
      "gv": [
        "3node",
        "1node",
        "0node",
        "2node",
        "4node"
      ],
      "JoinsReceived": 0,
      "ForwardJoinsReceived": 3,
      "ForwardJoinsSent": 1,
      "NeighborRequestsReceived": 0,
      "NeighborRequestsSent": 0,
      "DisconnectsReceived": 1,
      "DisconnectsSent": 0,
      "ShufflesReceived": 23,
      "ShufflesSent": 23,
      "BroadcastsSent": 12,
      "BroadcastsReceived": 9,
      "ResolveConflicts": 0,
      "ChecksIfAlive": 0
    },
    {
      "id": "0node",
      "av": [
        "3node",
        "4node"
      ],
      "pv": [
        "1node",
        "2node"
      ],
      "gv": [
        "3node",
        "1node",
        "0node",
        "2node",
        "4node"
      ],
      "JoinsReceived": 4,
      "ForwardJoinsReceived": 0,
      "ForwardJoinsSent": 3,
      "NeighborRequestsReceived": 7432,
      "NeighborRequestsSent": 0,
      "DisconnectsReceived": 0,
      "DisconnectsSent": 2,
      "ShufflesReceived": 21,
      "ShufflesSent": 23,
      "BroadcastsSent": 13,
      "BroadcastsReceived": 8,
      "ResolveConflicts": 0,
      "ChecksIfAlive": 0
    },
    {
      "id": "2node",
      "av": [
        "1node",
        "4node"
      ],
      "pv": [
        "3node",
        "0node"
      ],
      "gv": [
        "3node",
        "1node",
        "0node",
        "2node",
        "4node"
      ],
      "JoinsReceived": 0,
      "ForwardJoinsReceived": 2,
      "ForwardJoinsSent": 1,
      "NeighborRequestsReceived": 0,
      "NeighborRequestsSent": 14889,
      "DisconnectsReceived": 1,
      "DisconnectsSent": 0,
      "ShufflesReceived": 20,
      "ShufflesSent": 19,
      "BroadcastsSent": 8,
      "BroadcastsReceived": 12,
      "ResolveConflicts": 1,
      "ChecksIfAlive": 0
    }
  ]
}